logassert/__init__.py
logassert/logassert.py
logassert/pytest_plugin.py
logassert-8.6.dist-info/licenses/AUTHORS
logassert-8.6.dist-info/licenses/LICENSE
logassert-8.6.dist-info/METADATA
logassert-8.6.dist-info/WHEEL
logassert-8.6.dist-info/entry_points.txt
logassert-8.6.dist-info/top_level.txt
logassert-8.6.dist-info/RECORD
